MANIFEST.in
README.md
setup.cfg
setup.py
docs/.DS_Store
docs/Makefile
docs/conf.py
docs/index.rst
docs/make.bat
docs/User/.DS_Store
docs/User/API.rst
docs/User/installation.rst
docs/User/intro.rst
docs/User/quick_start.rst
docs/User/API/.DS_Store
docs/User/API/cache.rst
docs/User/API/cacheReader.rst
docs/User/API/cachecow.rst
docs/User/API/profiler.rst
docs/User/AdvancedUsage/advanced_usage.rst
docs/User/Tutorial/basic_plotting.rst
docs/User/Tutorial/heatmap_plotting.rst
docs/User/Tutorial/open_trace.rst
docs/User/Tutorial/profiling.rst
docs/User/appendix/algorithms.rst
docs/User/del/.DS_Store
docs/User/del/more_usage.rst1
docs/User/del/ref.rst1
docs/images/architecture.png
docs/images/basicPlotting_HRCs.png
docs/images/example_3D.png
docs/images/example_HRC.png
docs/images/example_MRC.png
docs/images/example_cold_miss2d.png
docs/images/example_differential_heatmap.png
docs/images/example_heatmap_rd_distibution.png
docs/images/example_mappingplot.png
docs/images/example_request_num.png
docs/images/github_HRC.png
docs/images/github_heatmap.png
mimircache/__init__.py
mimircache/const.py
mimircache/version.py
mimircache.egg-info/PKG-INFO
mimircache.egg-info/SOURCES.txt
mimircache.egg-info/dependency_links.txt
mimircache.egg-info/requires.txt
mimircache.egg-info/top_level.txt
mimircache/CExtension/cache/AMP.c
mimircache/CExtension/cache/ARC.c
mimircache/CExtension/cache/FIFO.c
mimircache/CExtension/cache/LFU.c
mimircache/CExtension/cache/LFUFast.c
mimircache/CExtension/cache/LRFU.c
mimircache/CExtension/cache/LRU.c
mimircache/CExtension/cache/LRUPage.c
mimircache/CExtension/cache/LRUSize.c
mimircache/CExtension/cache/LRU_K.c
mimircache/CExtension/cache/MRU.c
mimircache/CExtension/cache/Optimal.c
mimircache/CExtension/cache/PG.c
mimircache/CExtension/cache/Random.c
mimircache/CExtension/cache/SLRU.c
mimircache/CExtension/cache/SLRUML.c
mimircache/CExtension/cache/Score.c
mimircache/CExtension/cache/akamai.c
mimircache/CExtension/cache/cache.c
mimircache/CExtension/cache/mimir.c
mimircache/CExtension/cache/new1.c
mimircache/CExtension/cache/new2.c
mimircache/CExtension/cache/include/AMP.h
mimircache/CExtension/cache/include/ARC.h
