Metadata-Version: 1.1
Name: mimircache
Version: 0.0.2.85
Summary: mimircache platform for analyzing cache traces, developed by Juncheng Yang in Ymir group @ Emory University
Home-page: http://mimircache.info
Author: Juncheng Yang
Author-email: peter.waynechina@gmail.com
License: GPLv3
Keywords: mimircache cache Ymir
Platform: UNKNOWN
Classifier: Development Status :: 3 - Alpha
Classifier: Programming Language :: Python :: 3.3
Classifier: Programming Language :: Python :: 3.4
Classifier: Programming Language :: Python :: 3.5
